Metadata-Version: 2.4
Name: samestr
Version: 1.2025.111
Summary: SameStr identifies shared strains between pairs of metagenomic samples based on the similarity of SNV profiles.
Home-page: https://github.com/danielpodlesny/samestr/
Author: Daniel Podlesny
Author-email: Daniel Podlesny <daniel.podlesny@embl.de>
License:                     GNU AFFERO GENERAL PUBLIC LICENSE
Project-URL: Homepage, https://github.com/danielpodlesny/samestr
Project-URL: Bug Tracker, https://github.com/danielpodlesny/samestr/issues
Project-URL: Publication, https://doi.org/10.1186/s40168-022-01251-w
Classifier: Programming Language :: Python :: 3
Classifier: Topic :: Scientific/Engineering :: Bio-Informatics
Classifier: Intended Audience :: Science/Research
Classifier: Operating System :: POSIX :: Linux
Classifier: Environment :: Console
Classifier: Natural Language :: English
Requires-Python: >=3.9
License-File: LICENSE
Dynamic: author
Dynamic: home-page
Dynamic: license-file
